securionpay/__init__.py
securionpay/__version__.py
securionpay/blacklist.py
securionpay/cards.py
securionpay/charges.py
securionpay/checkout_request.py
securionpay/credits.py
securionpay/cross_sale_offers.py
securionpay/customers.py
securionpay/disputes.py
securionpay/events.py
securionpay/exception.py
securionpay/file_uploads.py
securionpay/fraud_warnings.py
securionpay/payment_methods.py
securionpay/plans.py
securionpay/resource.py
securionpay/subscriptions.py
securionpay/tokens.py
securionpay-2.1.0.dist-info/LICENSE
securionpay-2.1.0.dist-info/METADATA
securionpay-2.1.0.dist-info/WHEEL
securionpay-2.1.0.dist-info/top_level.txt
securionpay-2.1.0.dist-info/RECORD
