Metadata-Version: 2.1
Name: securionpay
Version: 2.1.0
Summary: Python library for SecurionPay API
Home-page: https://github.com/securionpay/securionpay-python
Author: SecurionPay Team
Author-email: support@securionpay.com
License: MIT
Keywords: payment
Classifier: Development Status :: 5 - Production/Stable
Classifier: Intended Audience :: Developers
Classifier: Topic :: Software Development :: Build Tools
Classifier: License :: OSI Approved :: MIT License
Classifier: Programming Language :: Python :: 3.7
Classifier: Programming Language :: Python :: 3.8
Classifier: Programming Language :: Python :: 3.9
Classifier: Programming Language :: Python :: 3.10
Classifier: Programming Language :: Python :: 3.11
License-File: LICENSE
Requires-Dist: requests (>=2.27.1)
